{
  "album_id": {
    "value": 210803679
  },
  "photos": {
    "355547601": {
      "photo_id": {
        "value": 355547601
      },
      "vkLink": "https://vk.com/photo-62111632_355547601",
      "album_id": {
        "value": 210803679
      },
      "user_id": {
        "value": 100
      },
      "date": {
        "timestamp": 1423153436000,
        "javaDate": "Feb 5, 2015 5:23:56 PM"
      },
      "text": "Что может быть красивее лисички? Только рисунок с лисой! \nВот и мы так думаем. \nПриглашаем приобщиться к няшному прямо сейчас. Рисуем лис, лисят, лисок и лисичичек. Впустите милоту в вашу жизнь :)\n#плашка"
    },
    "357575429": {
      "photo_id": {
        "value": 357575429
      },
      "vkLink": "https://vk.com/photo-62111632_357575429",
      "album_id": {
        "value": 210803679
      },
      "user_id": {
        "value": 100
      },
      "date": {
        "timestamp": 1424732099000,
        "javaDate": "Feb 23, 2015 11:54:59 PM"
      },
      "text": "Тамри Нижарадзе\nhttps://vk.com/tamroid\n---------------------\nТамри Нижарадзе\nhttps://vk.com/id554008\n"
    },
    "355547739": {
      "photo_id": {
        "value": 355547739
      },
      "vkLink": "https://vk.com/photo-62111632_355547739",
      "album_id": {
        "value": 210803679
      },
      "user_id": {
        "value": 100
      },
      "date": {
        "timestamp": 1423153502000,
        "javaDate": "Feb 5, 2015 5:25:02 PM"
      },
      "text": "Quiet Victories\nquiet-victories.tumblr.com\n\nЛучше чем пропустить дедлайн в третий раз- нарисовать немедленно и не затягивая.\n---------------------\nSpeech Freedom\nhttps://vk.com/id19407085\n"
    },
    "355547735": {
      "photo_id": {
        "value": 355547735
      },
      "vkLink": "https://vk.com/photo-62111632_355547735",
      "album_id": {
        "value": 210803679
      },
      "user_id": {
        "value": 100
      },
      "date": {
        "timestamp": 1423153501000,
        "javaDate": "Feb 5, 2015 5:25:01 PM"
      },
      "text": "Марина Сигунова\nhttps://vk.com/drakonoobraznoe\n\nПынь."
    },
    "355547741": {
      "photo_id": {
        "value": 355547741
      },
      "vkLink": "https://vk.com/photo-62111632_355547741",
      "album_id": {
        "value": 210803679
      },
      "user_id": {
        "value": 100
      },
      "date": {
        "timestamp": 1423153503000,
        "javaDate": "Feb 5, 2015 5:25:03 PM"
      },
      "text": "Юлия Яковлева\nhttps://vk.com/id76807738"
    },
    "355547698": {
      "photo_id": {
        "value": 355547698
      },
      "vkLink": "https://vk.com/photo-62111632_355547698",
      "album_id": {
        "value": 210803679
      },
      "user_id": {
        "value": 100
      },
      "date": {
        "timestamp": 1423153492000,
        "javaDate": "Feb 5, 2015 5:24:52 PM"
      },
      "text": "Александра Кела\nhttps://vk.com/id53503028\n\n(упс, мы потеряли описание)"
    },
    "355547726": {
      "photo_id": {
        "value": 355547726
      },
      "vkLink": "https://vk.com/photo-62111632_355547726",
      "album_id": {
        "value": 210803679
      },
      "user_id": {
        "value": 100
      },
      "date": {
        "timestamp": 1423153499000,
        "javaDate": "Feb 5, 2015 5:24:59 PM"
      },
      "text": "Lenni Gardden\nhttp://lennigen.deviantart.com/"
    },
    "355547721": {
      "photo_id": {
        "value": 355547721
      },
      "vkLink": "https://vk.com/photo-62111632_355547721",
      "album_id": {
        "value": 210803679
      },
      "user_id": {
        "value": 100
      },
      "date": {
        "timestamp": 1423153498000,
        "javaDate": "Feb 5, 2015 5:24:58 PM"
      },
      "text": "Саша Богатов\nvk.com/drop_shadow\nbehance.net/belk1n\n\nГородская лиса.\n---------------------\nСаша Богатов\nhttps://vk.com/id6931933\n"
    },
    "355547723": {
      "photo_id": {
        "value": 355547723
      },
      "vkLink": "https://vk.com/photo-62111632_355547723",
      "album_id": {
        "value": 210803679
      },
      "user_id": {
        "value": 100
      },
      "date": {
        "timestamp": 1423153499000,
        "javaDate": "Feb 5, 2015 5:24:59 PM"
      },
      "text": "Young Fox\nhttps://vk.com/artefaktlovely\n\nМоя лиса. Моя любовь.\n---------------------\nYoung Fox\nhttps://vk.com/id147718171\n"
    },
    "355547677": {
      "photo_id": {
        "value": 355547677
      },
      "vkLink": "https://vk.com/photo-62111632_355547677",
      "album_id": {
        "value": 210803679
      },
      "user_id": {
        "value": 100
      },
      "date": {
        "timestamp": 1423153483000,
        "javaDate": "Feb 5, 2015 5:24:43 PM"
      },
      "text": "Дерек Тернер\nhttps://vk.com/id173715288"
    },
    "355547684": {
      "photo_id": {
        "value": 355547684
      },
      "vkLink": "https://vk.com/photo-62111632_355547684",
      "album_id": {
        "value": 210803679
      },
      "user_id": {
        "value": 100
      },
      "date": {
        "timestamp": 1423153486000,
        "javaDate": "Feb 5, 2015 5:24:46 PM"
      },
      "text": "Анастасия Слободнюк\nhttp://nasty1009.deviantart.com/\n---------------------\nАнастасия Слободянюк\nhttps://vk.com/id3911041\n"
    },
    "355558673": {
      "photo_id": {
        "value": 355558673
      },
      "vkLink": "https://vk.com/photo-62111632_355558673",
      "album_id": {
        "value": 210803679
      },
      "user_id": {
        "value": 100
      },
      "date": {
        "timestamp": 1423158718000,
        "javaDate": "Feb 5, 2015 6:51:58 PM"
      },
      "text": "Полина Яковлева\nhttps://vk.com/keoning67\nhttp://virink.com/profile/keoning"
    },
    "357668306": {
      "photo_id": {
        "value": 357668306
      },
      "vkLink": "https://vk.com/photo-62111632_357668306",
      "album_id": {
        "value": 210803679
      },
      "user_id": {
        "value": 100
      },
      "date": {
        "timestamp": 1424807460000,
        "javaDate": "Feb 24, 2015 8:51:00 PM"
      },
      "text": "Night Dragoness\nhttps://vk.com/zariart\nhttp://zarielcharoitite.deviantart.com/\n\nнаверстываю упущенное х)\nмоя открытка с весенней лисичкой )\n---------------------\nNight Dragoness\nhttps://vk.com/id144158029\n"
    },
    "358423662": {
      "photo_id": {
        "value": 358423662
      },
      "vkLink": "https://vk.com/photo-62111632_358423662",
      "album_id": {
        "value": 210803679
      },
      "user_id": {
        "value": 100
      },
      "date": {
        "timestamp": 1425414762000,
        "javaDate": "Mar 3, 2015 9:32:42 PM"
      },
      "text": "Ксения Африкантова\nhttp://vk.com/little_muy\nhttp://littlemuy.tumblr.com/\n\nУ всех весна, а мне осени хочется и на лисьем пикфайте хоть с запозданием, но поучаствовать.\nНасмотрелась Босиковых работ и получилось.^^\n---------------------\nКсения Африкантова\nhttps://vk.com/id20014105\n"
    },
    "360690944": {
      "photo_id": {
        "value": 360690944
      },
      "vkLink": "https://vk.com/photo-62111632_360690944",
      "album_id": {
        "value": 210803679
      },
      "user_id": {
        "value": 100
      },
      "date": {
        "timestamp": 1427184722000,
        "javaDate": "Mar 24, 2015 9:12:02 AM"
      },
      "text": "Night Dragoness\nhttp://zarielcharoitite.deviantart.com/\n\nполучилась вот такая еще открыточка с лисами х)"
    },
    "355547731": {
      "photo_id": {
        "value": 355547731
      },
      "vkLink": "https://vk.com/photo-62111632_355547731",
      "album_id": {
        "value": 210803679
      },
      "user_id": {
        "value": 100
      },
      "date": {
        "timestamp": 1423153501000,
        "javaDate": "Feb 5, 2015 5:25:01 PM"
      },
      "text": "Plum Tree - vk.com/id254834754"
    },
    "355583661": {
      "photo_id": {
        "value": 355583661
      },
      "vkLink": "https://vk.com/photo-62111632_355583661",
      "album_id": {
        "value": 210803679
      },
      "user_id": {
        "value": 100
      },
      "date": {
        "timestamp": 1423172958000,
        "javaDate": "Feb 5, 2015 10:49:18 PM"
      },
      "text": "Nothing To-Declare\nhttps://vk.com/wishofajellyfish\n\nОднажды ками послал кицунэ кусочек сыра:)\n---------------------\nМайя Эвридейайдро\nhttps://vk.com/id165552769\n"
    },
    "355559802": {
      "photo_id": {
        "value": 355559802
      },
      "vkLink": "https://vk.com/photo-62111632_355559802",
      "album_id": {
        "value": 210803679
      },
      "user_id": {
        "value": 100
      },
      "date": {
        "timestamp": 1423159273000,
        "javaDate": "Feb 5, 2015 7:01:13 PM"
      },
      "text": "Даниил Купершинский\nhttps://vk.com/kupedanila\n\nПростите за мусор в кадре, я не дома фоткал\n---------------------\nДаниил Купершинский\nhttps://vk.com/id35133094\n"
    },
    "355550687": {
      "photo_id": {
        "value": 355550687
      },
      "vkLink": "https://vk.com/photo-62111632_355550687",
      "album_id": {
        "value": 210803679
      },
      "user_id": {
        "value": 100
      },
      "date": {
        "timestamp": 1423155057000,
        "javaDate": "Feb 5, 2015 5:50:57 PM"
      },
      "text": "Елена Шляхова\nhttps://vk.com/alenapanterka\n---------------------\nАлёна Медведева\nhttps://vk.com/id47403389\n"
    },
    "355550062": {
      "photo_id": {
        "value": 355550062
      },
      "vkLink": "https://vk.com/photo-62111632_355550062",
      "album_id": {
        "value": 210803679
      },
      "user_id": {
        "value": 100
      },
      "date": {
        "timestamp": 1423154724000,
        "javaDate": "Feb 5, 2015 5:45:24 PM"
      },
      "text": "https://vk.com/id152666418\n*Где же ты?* \nЗдравствуйте,уважаемые.Я всегда хотела поучаствовать,но увы,я такой ленивый:с\nОднако,вот моя первая \"здешняя\" работа.\nЯ рисую только в традишке и надеюсь,что вам понравится.\nС любовью,борщ."
    },
    "355547683": {
      "photo_id": {
        "value": 355547683
      },
      "vkLink": "https://vk.com/photo-62111632_355547683",
      "album_id": {
        "value": 210803679
      },
      "user_id": {
        "value": 100
      },
      "date": {
        "timestamp": 1423153486000,
        "javaDate": "Feb 5, 2015 5:24:46 PM"
      },
      "text": "Катерина Гуляева\nhttps://vk.com/kato_goo\n---------------------\nКатерина Гуляева\nhttps://vk.com/id1045364\n"
    },
    "355547680": {
      "photo_id": {
        "value": 355547680
      },
      "vkLink": "https://vk.com/photo-62111632_355547680",
      "album_id": {
        "value": 210803679
      },
      "user_id": {
        "value": 100
      },
      "date": {
        "timestamp": 1423153485000,
        "javaDate": "Feb 5, 2015 5:24:45 PM"
      },
      "text": "My Moon\nhttps://vk.com/id163524476\n\nПикфайт #31 «Лисы»"
    },
    "355547743": {
      "photo_id": {
        "value": 355547743
      },
      "vkLink": "https://vk.com/photo-62111632_355547743",
      "album_id": {
        "value": 210803679
      },
      "user_id": {
        "value": 100
      },
      "date": {
        "timestamp": 1423153503000,
        "javaDate": "Feb 5, 2015 5:25:03 PM"
      },
      "text": "Катерина Шмырина\nhttp://vk.com/art_kotan\n---------------------\nКатерина Шмырина\nhttps://vk.com/id562753\n"
    },
    "355547678": {
      "photo_id": {
        "value": 355547678
      },
      "vkLink": "https://vk.com/photo-62111632_355547678",
      "album_id": {
        "value": 210803679
      },
      "user_id": {
        "value": 100
      },
      "date": {
        "timestamp": 1423153484000,
        "javaDate": "Feb 5, 2015 5:24:44 PM"
      },
      "text": "Таня Босик\nhttp://vk.com/tanyabosyk_art\n---------------------\nТаня Лобач\nhttps://vk.com/id38545546\n"
    },
    "355547686": {
      "photo_id": {
        "value": 355547686
      },
      "vkLink": "https://vk.com/photo-62111632_355547686",
      "album_id": {
        "value": 210803679
      },
      "user_id": {
        "value": 100
      },
      "date": {
        "timestamp": 1423153487000,
        "javaDate": "Feb 5, 2015 5:24:47 PM"
      },
      "text": "Анастасия Кушнаренко\nhttps://vk.com/unmag\n\nНемного упоротости еще никому не повредило (:"
    },
    "355547688": {
      "photo_id": {
        "value": 355547688
      },
      "vkLink": "https://vk.com/photo-62111632_355547688",
      "album_id": {
        "value": 210803679
      },
      "user_id": {
        "value": 100
      },
      "date": {
        "timestamp": 1423153488000,
        "javaDate": "Feb 5, 2015 5:24:48 PM"
      },
      "text": "Анна Клевцова\nhttp://vk.com/mamamelanholia\nhttp://virink.com/profile/mamamelanholia\nhttps://vk.com/id81558869\n\nЛиса Патрикеевна"
    },
    "355547695": {
      "photo_id": {
        "value": 355547695
      },
      "vkLink": "https://vk.com/photo-62111632_355547695",
      "album_id": {
        "value": 210803679
      },
      "user_id": {
        "value": 100
      },
      "date": {
        "timestamp": 1423153492000,
        "javaDate": "Feb 5, 2015 5:24:52 PM"
      },
      "text": "Марк Хамстов\nhttp://vk.com/ogromnaya_kuritca\n\nне смог в фон :с\n---------------------\nМарк Хамстов\nhttps://vk.com/id182454635\n"
    },
    "355547727": {
      "photo_id": {
        "value": 355547727
      },
      "vkLink": "https://vk.com/photo-62111632_355547727",
      "album_id": {
        "value": 210803679
      },
      "user_id": {
        "value": 100
      },
      "date": {
        "timestamp": 1423153500000,
        "javaDate": "Feb 5, 2015 5:25:00 PM"
      },
      "text": "Екатерина Калмыкова\n vk.com/flvix\nvk.com/flvix_ill\n\nЛисик :)\nДавно хотела нарисовать лисенка-персонажа)\n---------------------\nЕкатерина Калмыкова\nhttps://vk.com/id72679491\n"
    },
    "355547701": {
      "photo_id": {
        "value": 355547701
      },
      "vkLink": "https://vk.com/photo-62111632_355547701",
      "album_id": {
        "value": 210803679
      },
      "user_id": {
        "value": 100
      },
      "date": {
        "timestamp": 1423153493000,
        "javaDate": "Feb 5, 2015 5:24:53 PM"
      },
      "text": "Настя Андреева\nhttps://vk.com/nind2014\n\nЯ первый раз участвую в таком мероприятии. Рисовать отсилы могу......\n---------------------\nНастя Индейкина\nhttps://vk.com/id232351096\n"
    },
    "355547705": {
      "photo_id": {
        "value": 355547705
      },
      "vkLink": "https://vk.com/photo-62111632_355547705",
      "album_id": {
        "value": 210803679
      },
      "user_id": {
        "value": 100
      },
      "date": {
        "timestamp": 1423153494000,
        "javaDate": "Feb 5, 2015 5:24:54 PM"
      },
      "text": "Яна-Мария Пристли\ntwitter: evita_priestley\ninstagram: yanamariapriestley\n\nпредлагаю лисью новость!"
    },
    "355547708": {
      "photo_id": {
        "value": 355547708
      },
      "vkLink": "https://vk.com/photo-62111632_355547708",
      "album_id": {
        "value": 210803679
      },
      "user_id": {
        "value": 100
      },
      "date": {
        "timestamp": 1423153495000,
        "javaDate": "Feb 5, 2015 5:24:55 PM"
      },
      "text": "Катя Попова\nhttps://vk.com/aki_ok\n\nФантастический и прекрасный Файрфокс\n---------------------\nКатя Попова\nhttps://vk.com/id8085642\n"
    },
    "355547712": {
      "photo_id": {
        "value": 355547712
      },
      "vkLink": "https://vk.com/photo-62111632_355547712",
      "album_id": {
        "value": 210803679
      },
      "user_id": {
        "value": 100
      },
      "date": {
        "timestamp": 1423153495000,
        "javaDate": "Feb 5, 2015 5:24:55 PM"
      },
      "text": "Юлия Anarhia\nhttps://vk.com/id70147644\n\nДоброго времени суток )))\nУ меня вот такой вот Лис, который немного запутался во времени и вселенных )"
    },
    "355547713": {
      "photo_id": {
        "value": 355547713
      },
      "vkLink": "https://vk.com/photo-62111632_355547713",
      "album_id": {
        "value": 210803679
      },
      "user_id": {
        "value": 100
      },
      "date": {
        "timestamp": 1423153496000,
        "javaDate": "Feb 5, 2015 5:24:56 PM"
      },
      "text": "Алтынай Валеева\nhttp://m.vk.com/moonygold\n\nВот моя 9-тихвостая лиса)"
    },
    "355547715": {
      "photo_id": {
        "value": 355547715
      },
      "vkLink": "https://vk.com/photo-62111632_355547715",
      "album_id": {
        "value": 210803679
      },
      "user_id": {
        "value": 100
      },
      "date": {
        "timestamp": 1423153496000,
        "javaDate": "Feb 5, 2015 5:24:56 PM"
      },
      "text": "Анна Щемерова\nhttps://vk.com/id12166282\n\nНочная прогулка. \nКартинка из серии \"первая проба\", но начало положено.\nСпасибо за тему, очень богатая! Все лисы, которые дремали во мне, выбрались наружу и настойчиво требуют своих пор"
    },
    "355547716": {
      "photo_id": {
        "value": 355547716
      },
      "vkLink": "https://vk.com/photo-62111632_355547716",
      "album_id": {
        "value": 210803679
      },
      "user_id": {
        "value": 100
      },
      "date": {
        "timestamp": 1423153497000,
        "javaDate": "Feb 5, 2015 5:24:57 PM"
      },
      "text": "Ирина Хараб\nhttps://vk.com/iren_kharab\n\n\"Полярная лисонька\"\n---------------------\nИрина Хараб\nhttps://vk.com/id27109931\n"
    }
  }
}