{
  "info": {
    "album_id": 252333010,
    "cover_id": 456240521,
    "title": "Пикфайт #69: «Доблестные воины пикфайтовых земель»",
    "description": "",
    "created": {
      "timestamp": 1521571667000,
      "javaDate": "Mar 20, 2018 7:47:47 PM"
    },
    "updated": {
      "timestamp": 1521571687000,
      "javaDate": "Mar 20, 2018 7:48:07 PM"
    },
    "vkLink": "https://vk.com/album-62111632_252333010"
  },
  "timastamp": {
    "timestamp": 1572119124661,
    "javaDate": "Oct 26, 2019 9:45:24 PM"
  },
  "likesFor": {
    "456240521": {
      "likesFrom": {
        "4858593": {},
        "144158029": {},
        "147718171": {},
        "229628592": {}
      }
    },
    "456240522": {
      "likesFrom": {
        "554008": {},
        "2092571": {},
        "3512268": {},
        "4111789": {},
        "4858593": {},
        "5355910": {},
        "7999404": {},
        "8581169": {},
        "8861808": {},
        "23036136": {},
        "39831712": {},
        "64831419": {},
        "115805033": {},
        "144158029": {},
        "161363454": {},
        "222087799": {},
        "229628592": {},
        "281836802": {},
        "288370294": {},
        "397894880": {},
        "452015837": {}
      }
    },
    "456240523": {
      "likesFrom": {
        "178616": {},
        "554008": {},
        "562753": {},
        "1349759": {},
        "3512268": {},
        "4858593": {},
        "5355910": {},
        "7999404": {},
        "28842197": {},
        "60478399": {},
        "64831419": {},
        "115805033": {},
        "144158029": {},
        "145356700": {},
        "147718171": {},
        "161363454": {},
        "177351379": {},
        "228363684": {},
        "229628592": {},
        "250358337": {},
        "281836802": {},
        "397894880": {},
        "452015837": {},
        "456775310": {},
        "496896027": {}
      }
    },
    "456240528": {
      "likesFrom": {
        "31993": {},
        "554008": {},
        "562753": {},
        "3512268": {},
        "4858593": {},
        "5355910": {},
        "7999404": {},
        "8581169": {},
        "20515210": {},
        "39831712": {},
        "64831419": {},
        "98968574": {},
        "114701061": {},
        "115805033": {},
        "138317702": {},
        "144158029": {},
        "147718171": {},
        "161363454": {},
        "171234415": {},
        "206090623": {},
        "228363684": {},
        "229628592": {},
        "235212507": {},
        "397894880": {},
        "452015837": {}
      }
    },
    "456240526": {
      "likesFrom": {
        "562753": {},
        "1349759": {},
        "2845964": {},
        "3512268": {},
        "4244395": {},
        "4648195": {},
        "4858593": {},
        "5355910": {},
        "6931933": {},
        "7999404": {},
        "8861808": {},
        "19318366": {},
        "20515210": {},
        "23036136": {},
        "36678151": {},
        "39831712": {},
        "48581269": {},
        "64831419": {},
        "98968574": {},
        "115805033": {},
        "139125457": {},
        "144158029": {},
        "145356700": {},
        "147718171": {},
        "161363454": {},
        "212514389": {},
        "229628592": {},
        "235212507": {},
        "288370294": {},
        "302968939": {},
        "452015837": {}
      }
    },
    "456240529": {
      "likesFrom": {
        "514558": {},
        "562753": {},
        "3144400": {},
        "3512268": {},
        "4858593": {},
        "5355910": {},
        "7999404": {},
        "11185692": {},
        "27039257": {},
        "64831419": {},
        "144158029": {},
        "147718171": {},
        "161363454": {},
        "236663748": {},
        "397894880": {},
        "452015837": {}
      }
    },
    "456240531": {
      "likesFrom": {
        "562753": {},
        "1349759": {},
        "3512268": {},
        "4858593": {},
        "5355910": {},
        "7999404": {},
        "28842197": {},
        "98968574": {},
        "114701061": {},
        "139125457": {},
        "144158029": {},
        "145356700": {},
        "147718171": {},
        "161363454": {},
        "397894880": {},
        "452015837": {}
      }
    },
    "456240527": {
      "likesFrom": {
        "562753": {},
        "4858593": {},
        "5355910": {},
        "7999404": {},
        "144158029": {},
        "147718171": {},
        "161363454": {}
      }
    },
    "456240525": {
      "likesFrom": {
        "554008": {},
        "562753": {},
        "3512268": {},
        "4648195": {},
        "4858593": {},
        "5355910": {},
        "7999404": {},
        "23036136": {},
        "36678151": {},
        "64831419": {},
        "98968574": {},
        "144158029": {},
        "145356700": {},
        "161363454": {},
        "190047300": {},
        "235212507": {},
        "345874277": {},
        "371272898": {},
        "452015837": {}
      }
    },
    "456240532": {
      "likesFrom": {
        "178616": {},
        "554008": {},
        "562753": {},
        "3512268": {},
        "4858593": {},
        "5355910": {},
        "7999404": {},
        "23036136": {},
        "36678151": {},
        "39831712": {},
        "102086161": {},
        "115805033": {},
        "134668967": {},
        "144158029": {},
        "161363454": {},
        "165144609": {},
        "225567547": {},
        "349316650": {},
        "397894880": {},
        "452015837": {}
      }
    },
    "456240530": {
      "likesFrom": {
        "178616": {},
        "554008": {},
        "562753": {},
        "1349759": {},
        "2028927": {},
        "2092571": {},
        "2537541": {},
        "3314701": {},
        "4244395": {},
        "4858593": {},
        "5355910": {},
        "7999404": {},
        "8581169": {},
        "8861808": {},
        "11954753": {},
        "12493476": {},
        "18567783": {},
        "28842197": {},
        "36678151": {},
        "39831712": {},
        "48581269": {},
        "64831419": {},
        "100337722": {},
        "102086161": {},
        "113915358": {},
        "115805033": {},
        "121507757": {},
        "139125457": {},
        "144158029": {},
        "145356700": {},
        "161363454": {},
        "165144609": {},
        "171633974": {},
        "171736020": {},
        "173715288": {},
        "187458552": {},
        "190047300": {},
        "191649717": {},
        "206090623": {},
        "216285500": {},
        "229628592": {},
        "235212507": {},
        "250358337": {},
        "309727755": {},
        "310517503": {},
        "317241220": {},
        "397894880": {},
        "429663095": {},
        "452015837": {},
        "496896027": {}
      }
    },
    "456240524": {
      "likesFrom": {
        "178616": {},
        "554008": {},
        "562753": {},
        "1349759": {},
        "2028927": {},
        "3512268": {},
        "4648195": {},
        "4858593": {},
        "5355910": {},
        "8861808": {},
        "28842197": {},
        "39831712": {},
        "64831419": {},
        "82322187": {},
        "100337722": {},
        "102086161": {},
        "115805033": {},
        "144158029": {},
        "145356700": {},
        "147718171": {},
        "161363454": {},
        "164199159": {},
        "220080551": {},
        "228363684": {},
        "229628592": {},
        "309727755": {},
        "397894880": {},
        "452015837": {},
        "456775310": {}
      }
    }
  }
}